{
  "cycles": 2080,
  "domains": {
    "learning": {
      "cycles": 2080,
      "blocked": 2080,
      "escalated": 2080,
      "total_decisions": 4160
    }
  },
  "entities": {
    "atlas://bot/organism-learning-bot": {
      "blocked": 2080,
      "allowed": 0,
      "escalated": 2080,
      "rules_triggered": 4160,
      "domain": "learning"
    }
  },
  "rules": {
    "governance://law/learning-stability#HALT_ON_REWARD_DIVERGENCE": {
      "triggered": 4160,
      "entities": [
        "atlas://bot/organism-learning-bot"
      ],
      "domains": [
        "learning"
      ]
    }
  },
  "updated_at": "2026-05-12T14:21:50.465Z"
}